[
  {
    "uid": "01kjmvb5m6yw8bt1frm10kbpfq",
    "assetUid": "01kjmvb59ywp9r2t3srmzsfvk2",
    "type": "4",
    "author": "Andrea Michelotti",
    "details": "{\"type\":\"4\",\"attribute\":\"Layout\",\"oldValue\":\"\",\"newValue\":\"M4-002\"}",
    "timestamp": "2023-12-01T14:24:18.000",
    "backendId": "186166"
  },
  {
    "uid": "01kjmvb5mcahym38qr0j3w7kq3",
    "assetUid": "01kjmvb59ywp9r2t3srmzsfvk2",
    "type": "1",
    "author": "Andrea Michelotti",
    "details": "{\"type\":\"1\",\"attribute\":\"Module\",\"oldValue\":\"\",\"newValue\":\"M4\"}",
    "timestamp": "2023-12-01T00:56:15.000",
    "backendId": "185540"
  },
  {
    "uid": "01kjmvb5me3amvzfmpz4brh6vg",
    "assetUid": "01kjmvb59ywp9r2t3srmzsfvk2",
    "type": "4",
    "author": "Andrea Michelotti",
    "details": "{\"type\":\"4\",\"attribute\":\"Next Element\",\"oldValue\":\"\",\"newValue\":\"LEL-DIA-SCN03:MOT01\"}",
    "timestamp": "2023-12-01T00:49:47.000",
    "backendId": "185421"
  },
  {
    "uid": "01kjmvb5mgsygxx57qd1hzxrtc",
    "assetUid": "01kjmvb59ywp9r2t3srmzsfvk2",
    "type": "4",
    "author": "Andrea Michelotti",
    "details": "{\"type\":\"4\",\"attribute\":\"Previous Element\",\"oldValue\":\"\",\"newValue\":\"LEL-MAG-HCOR06\"}",
    "timestamp": "2023-12-01T00:49:47.000",
    "backendId": "185420"
  },
  {
    "uid": "01kjmvb5mhgfc565hqkcyexrds",
    "assetUid": "01kjmvb59ywp9r2t3srmzsfvk2",
    "type": "0",
    "author": "Andrea Michelotti",
    "details": "{\"type\":\"0\"}",
    "timestamp": "2023-12-01T00:37:38.000",
    "backendId": "185282"
  }
]