[
  {
    "uid": "01kjmv2k1601x8bq2psv84e65r",
    "assetUid": "01kjmv2jrb0wcgtg6cxxjj0s67",
    "type": "1",
    "author": "Andrea Michelotti",
    "details": "{\"type\":\"1\",\"attribute\":\"Description\",\"oldValue\":\"\",\"newValue\":\"BTF/Dafne\"}",
    "timestamp": "2025-09-02T13:44:58.000",
    "backendId": "341498"
  },
  {
    "uid": "01kjmv2k1dzcddwvpxxg7qfc21",
    "assetUid": "01kjmv2jrb0wcgtg6cxxjj0s67",
    "type": "0",
    "author": "Andrea Michelotti",
    "details": "{\"type\":\"0\"}",
    "timestamp": "2025-09-02T13:44:44.000",
    "backendId": "341497"
  }
]