[
  {
    "uid": "01kjmvbyat8b35vve5yjb3s0qv",
    "assetUid": "01kjmvbxafjtxcskzbw2b4qmw7",
    "schemaUid": "01kjmv6qvztcs41475w4v17vnh",
    "filename": "CPSU03.jpg",
    "mimeType": "image/jpeg",
    "fileSize": 3501523,
    "author": "amichelo",
    "created": "2025-06-12T17:19:45.000",
    "binaryPath": "schemas/LNF ELI NP/HW asset/powersupply/assets/LEL-MAG-CPSU03/attachments/CPSU03.jpg",
    "originBackendId": "2483",
    "originUrl": "https://servicedesk.infn.it/rest/insight/1.0/attachments/2483/CPSU03.jpg"
  }
]