[
  {
    "uid": "01kjmvbgmx6jthm8pn8wfc4kcy",
    "assetUid": "01kjmvbg9w99asx2jcyeskxmfg",
    "type": "4",
    "author": "Andrea Michelotti",
    "details": "{\"type\":\"4\",\"attribute\":\"Layout\",\"oldValue\":\"\",\"newValue\":\"M1-014\"}",
    "timestamp": "2023-12-01T14:23:12.000"
  },
  {
    "uid": "01kjmvbgn04vw5v1cv0ts4cy7p",
    "assetUid": "01kjmvbg9w99asx2jcyeskxmfg",
    "type": "1",
    "author": "Andrea Michelotti",
    "details": "{\"type\":\"1\",\"attribute\":\"Module\",\"oldValue\":\"\",\"newValue\":\"M1\"}",
    "timestamp": "2023-12-01T00:55:55.000"
  },
  {
    "uid": "01kjmvbgn2sm1j02s2eet2gcty",
    "assetUid": "01kjmvbg9w99asx2jcyeskxmfg",
    "type": "4",
    "author": "Andrea Michelotti",
    "details": "{\"type\":\"4\",\"attribute\":\"Next Element\",\"oldValue\":\"\",\"newValue\":\"LEL-VAC-VALVM02\"}",
    "timestamp": "2023-12-01T00:49:22.000"
  },
  {
    "uid": "01kjmvbgn5r2wb12qf2j1z7gms",
    "assetUid": "01kjmvbg9w99asx2jcyeskxmfg",
    "type": "4",
    "author": "Andrea Michelotti",
    "details": "{\"type\":\"4\",\"attribute\":\"Previous Element\",\"oldValue\":\"\",\"newValue\":\"LEL-MAG-VCOR01\"}",
    "timestamp": "2023-12-01T00:49:22.000"
  },
  {
    "uid": "01kjmvbgn6xrrj5dxhdw6gg793",
    "assetUid": "01kjmvbg9w99asx2jcyeskxmfg",
    "type": "0",
    "author": "Andrea Michelotti",
    "details": "{\"type\":\"0\"}",
    "timestamp": "2023-12-01T00:37:09.000"
  }
]