{
  "uid": "01kjmv611pvqqn8tbsfgb7rsxp",
  "name": "Avatar for Dafne",
  "localPath": "/data/user/0/com.michelo.asset_app/app_flutter/avatars/01kjmv611pvqqn8tbsfgb7rsxp.png",
  "sourceUrl": "https://servicedesk.infn.it/rest/insight/1.0/objecttype/1435/icon.png?size=288&uuid=78b0109b-d205-4b22-b524-5e600cd6bc8e",
  "linkedSchemaUid": null,
  "linkedAssetUid": "01kjmv60y5dm04w7hfezx8kd9q",
  "fileSize": 448,
  "mimeType": "image/png",
  "createdAt": "2026-03-01T15:00:07.478148",
  "updatedAt": "2026-03-01T15:00:07.478148",
  "backendType": "jira",
  "backendIconId": null
}