{
  "uid": "01kjmv6xw8vmmbt45sax9bemky",
  "name": "Avatar for sw-oxgs-ssrip-roof",
  "sourceUrl": "https://servicedesk.infn.it/rest/insight/1.0/object/138419/avatar.png?size=288&time=1749800704000",
  "linkedSchemaUid": null,
  "linkedAssetUid": "01kjmv6xj3ra3v3q4xj25dhy1c",
  "fileSize": 280391,
  "mimeType": "image/png",
  "createdAt": "2026-03-01T15:00:37.000951",
  "updatedAt": "2026-03-01T15:00:37.000951",
  "backendType": "jira",
  "backendIconId": null,
  "binaryPath": "icons/files/01kjmv6xj3ra3v3q4xj25dhy1c/Avatar for sw-oxgs-ssrip-roof"
}