{
  "uid": "01kjmv3ac00dgg576nkgndgh04",
  "name": "Avatar for NPort 5450",
  "sourceUrl": "https://servicedesk.infn.it/rest/insight/1.0/object/137631/avatar.png?size=288&time=1747751012000",
  "linkedSchemaUid": null,
  "linkedAssetUid": "01kjmv3a7zxyrj2cc3yhc7d8xx",
  "fileSize": 86515,
  "mimeType": "image/png",
  "createdAt": "2026-03-01T14:58:38.720996",
  "updatedAt": "2026-03-01T14:58:38.720996",
  "backendType": "jira",
  "backendIconId": null,
  "binaryPath": "icons/files/01kjmv3a7zxyrj2cc3yhc7d8xx/Avatar for NPort 5450"
}