{
  "uid": "01kjr89pdxa465zng097s0y3h4",
  "key": "LNFELINP-112562",
  "name": "R_ROOF_INFN10",
  "type": "Beamline Assets",
  "schemaUid": "01kjr7v5j1psjrgx3cv2mkh5wf",
  "attributes": {
    "key": "LNFELINP-112562",
    "name": "R_ROOF_INFN10",
    "created": "2023-12-01T13:15:48.000Z",
    "updated": "2023-12-01T13:15:48.000Z"
  },
  "relations": {
    "inbound": [],
    "outbound": []
  },
  "attachments": [],
  "metadata": {
    "createdAt": null,
    "updatedAt": null,
    "version": null
  }
}