{
  "uid": "01kjmt81721d4kgk5ff3bjxj3s",
  "key": "LNFMAC-106298",
  "name": "POSITRONS MAIN RING - PS2",
  "type": "Locations Accelerator Division",
  "schemaUid": "01kjmt347jhyr9ke7ft6qbt0b5",
  "attributes": {
    "key": "LNFMAC-106298",
    "name": "POSITRONS MAIN RING - PS2",
    "created": "2023-09-30T17:10:45.000Z",
    "updated": "2025-10-28T14:52:13.000Z",
    "description": "<p>Short arc from the symmetry point to IR2</p>"
  },
  "relations": {
    "inbound": [],
    "outbound": []
  },
  "attachments": [],
  "metadata": {
    "createdAt": null,
    "updatedAt": null,
    "version": null
  }
}