{
  "uid": "01kjmtxc50htzg4pqcd5z9wxvj",
  "key": "LNFELINP-112041",
  "name": "IONP11-CAB054",
  "type": "Cabling",
  "schemaUid": "01kjmswgzg2ysjf4bv45zx0f1h",
  "attributes": {
    "key": "LNFELINP-112041",
    "name": "IONP11-CAB054",
    "created": "2023-11-30T12:23:53.000Z",
    "updated": "2025-02-27T08:29:33.000Z",
    "description": "Ion pump 75 l/s",
    "connector1_pair": "01kjmtbpt2546qd9hqpaqe6kr7",
    "connector1_desc": "fischer K105A049 d5.2 + Banana socket",
    "connector2_desc": "fischer S105A049 d5.2 + Banana Plug",
    "connection_type_desc": "solder",
    "cable_type_desc": "CEAM RG58HV 7.5 kV + interlock 2x0.75"
  },
  "relations": {
    "inbound": [],
    "outbound": []
  },
  "attachments": [],
  "metadata": {
    "createdAt": null,
    "updatedAt": null,
    "version": null
  }
}