{
  "uid": "01kjmtyhen6d9d6qzje071rk9b",
  "key": "LNFELINP-138467",
  "name": "VPCON1-ser",
  "type": "Cabling",
  "schemaUid": "01kjmswgzg2ysjf4bv45zx0f1h",
  "attributes": {
    "key": "LNFELINP-138467",
    "name": "VPCON1-ser",
    "created": "2025-06-13T12:12:40.000Z",
    "updated": "2025-12-06T22:56:14.000Z",
    "status": "Active",
    "location": "01kjmtf8m7fd1x5f4bs7s0jtpj",
    "connector2_pair": "01kjmtdb3bjgdm1qxfm3dxqkyy",
    "connector2_desc": "<div class=\"created-with-ak-editor content-wrapper\"><p>port 6</p></div>",
    "cable_type_desc": "<div class=\"created-with-ak-editor content-wrapper\"><p>3 meter long </p></div>",
    "type": "RS232",
    "lenght": "3"
  },
  "relations": {
    "inbound": [],
    "outbound": []
  },
  "attachments": [],
  "metadata": {
    "createdAt": null,
    "updatedAt": null,
    "version": null
  }
}