{
  "uid": "01kjmt8ney3xy8np7xayqy0yn9",
  "key": "LNFMAC-100330",
  "name": "Sala Strumentazione - Rack 035",
  "type": "Locations Accelerator Division",
  "schemaUid": "01kjmt347jhyr9ke7ft6qbt0b5",
  "attributes": {
    "key": "LNFMAC-100330",
    "name": "Sala Strumentazione - Rack 035",
    "created": "2023-06-12T16:11:03.000Z",
    "updated": "2025-10-28T14:52:13.000Z"
  },
  "relations": {
    "inbound": [],
    "outbound": []
  },
  "attachments": [],
  "metadata": {
    "createdAt": null,
    "updatedAt": null,
    "version": null
  }
}