[
  {
    "uid": "01kjr7r3pb336rmkeaf0jze0s9",
    "assetUid": "01kjr7r3638nrvbvf5e52hrpfp",
    "type": "29",
    "author": "Martina Del Giorno",
    "details": "{\"type\":\"29\"}",
    "timestamp": "2025-10-28T15:52:12.000"
  },
  {
    "uid": "01kjr7r3pktj2sg293ahg9fnk9",
    "assetUid": "01kjr7r3638nrvbvf5e52hrpfp",
    "type": "28",
    "author": "Martina Del Giorno",
    "details": "{\"type\":\"28\"}",
    "timestamp": "2025-10-28T15:49:10.000"
  },
  {
    "uid": "01kjr7r3ps7h24xy9n0rtazsxh",
    "assetUid": "01kjr7r3638nrvbvf5e52hrpfp",
    "type": "24",
    "author": "Martina Del Giorno",
    "details": "{\"type\":\"24\",\"oldValue\":\"Location\",\"newValue\":\"FLAME Ed 56\"}",
    "timestamp": "2025-10-28T15:47:28.000"
  },
  {
    "uid": "01kjr7r3py3ng2m8gk5knxz97r",
    "assetUid": "01kjr7r3638nrvbvf5e52hrpfp",
    "type": "0",
    "author": "Unknown",
    "details": "{\"type\":\"0\"}",
    "timestamp": "2023-06-12T15:36:54.000"
  }
]