[
  {
    "uid": "01kjmvk3b3q4v39e1753m6xcgw",
    "assetUid": "01kjmvk30wtab419fk27fpfs6g",
    "type": "26",
    "author": "Georgios Zachariadis",
    "details": "{\"type\":\"26\"}",
    "timestamp": "2025-06-13T12:00:19.000",
    "backendId": "321731"
  },
  {
    "uid": "01kjmvk3b9r1t00z1bzgc2wffj",
    "assetUid": "01kjmvk30wtab419fk27fpfs6g",
    "type": "25",
    "author": "Georgios Zachariadis",
    "details": "{\"type\":\"25\"}",
    "timestamp": "2025-06-13T10:38:24.000",
    "backendId": "321724"
  },
  {
    "uid": "01kjmvk3bdsbmv0qywf1jkn45p",
    "assetUid": "01kjmvk30wtab419fk27fpfs6g",
    "type": "4",
    "author": "Georgios Zachariadis",
    "details": "{\"type\":\"4\",\"attribute\":\"Model\",\"oldValue\":\"\",\"newValue\":\"Libera LLRF\"}",
    "timestamp": "2025-06-13T09:56:09.000",
    "backendId": "321721"
  },
  {
    "uid": "01kjmvk3bfpfzy1xwd8vt10scv",
    "assetUid": "01kjmvk30wtab419fk27fpfs6g",
    "type": "4",
    "author": "Georgios Zachariadis",
    "details": "{\"type\":\"4\",\"attribute\":\"Rack\",\"oldValue\":\"\",\"newValue\":\"R_RUF_04\"}",
    "timestamp": "2025-06-13T09:56:09.000",
    "backendId": "321720"
  },
  {
    "uid": "01kjmvk3bh00dy9pwedvw7wvm6",
    "assetUid": "01kjmvk30wtab419fk27fpfs6g",
    "type": "4",
    "author": "Georgios Zachariadis",
    "details": "{\"type\":\"4\",\"attribute\":\"Location\",\"oldValue\":\"\",\"newValue\":\"ROOF\"}",
    "timestamp": "2025-06-13T09:56:09.000",
    "backendId": "321719"
  },
  {
    "uid": "01kjmvk3bkjv8cs7y6zmhgn2w9",
    "assetUid": "01kjmvk30wtab419fk27fpfs6g",
    "type": "1",
    "author": "Georgios Zachariadis",
    "details": "{\"type\":\"1\",\"attribute\":\"Description\",\"oldValue\":\"\",\"newValue\":\"ELI - S-BAND Libe...\"}",
    "timestamp": "2025-06-13T09:56:09.000",
    "backendId": "321718"
  },
  {
    "uid": "01kjmvk3bnftk05tnm47jx03jt",
    "assetUid": "01kjmvk30wtab419fk27fpfs6g",
    "type": "0",
    "author": "Andrea Michelotti",
    "details": "{\"type\":\"0\"}",
    "timestamp": "2025-06-13T06:30:26.000",
    "backendId": "321700"
  }
]