{
  "uid": "01kjr7d4zr64297nqfgg3809ga",
  "key": "LNFMAC-109321",
  "name": "S&D INTERNATIONAL S.R.L.",
  "type": "Company",
  "schemaUid": "01kjr7a25r0qb0me3r75z7mdqx",
  "attributes": {
    "key": "LNFMAC-109321",
    "name": "S&D INTERNATIONAL S.R.L.",
    "created": "2023-10-10T12:39:07.000Z",
    "updated": "2023-10-10T12:39:07.000Z",
    "contact": "S&D INTERNATIONAL S.R.L."
  },
  "relations": {
    "inbound": [],
    "outbound": []
  },
  "attachments": [],
  "metadata": {
    "createdAt": null,
    "updatedAt": null,
    "version": null
  }
}