[
  {
    "uid": "01kjr7xrh3wgxh3m88b6wrfefh",
    "assetUid": "01kjr7xqw0kr6fq3sdqjd5e4vy",
    "type": "5",
    "author": "Georgios Zachariadis",
    "details": "{\"type\":\"5\",\"attribute\":\"Controller\",\"oldValue\":\"LEL-VAC-WGS01:VPC...\",\"newValue\":\"LEL-VAC-WGS01:VPC...\"}",
    "timestamp": "2025-11-06T17:50:10.000"
  },
  {
    "uid": "01kjr7xrhvhnvw7h474c8xpc06",
    "assetUid": "01kjr7xqw0kr6fq3sdqjd5e4vy",
    "type": "2",
    "author": "Georgios Zachariadis",
    "details": "{\"type\":\"2\",\"attribute\":\"Description\",\"oldValue\":\"Vacuum Ion Pump\",\"newValue\":\"Vacuum Ion Pump\"}",
    "timestamp": "2025-11-06T17:50:10.000"
  },
  {
    "uid": "01kjr7xrj7v9wsabkwntmpjnb3",
    "assetUid": "01kjr7xqw0kr6fq3sdqjd5e4vy",
    "type": "4",
    "author": "Andrea Michelotti",
    "details": "{\"type\":\"4\",\"attribute\":\"Layout\",\"oldValue\":\"\",\"newValue\":\"WGS02-003\"}",
    "timestamp": "2023-12-01T14:15:40.000"
  },
  {
    "uid": "01kjr7xrje3zcqat0hvc2gr10a",
    "assetUid": "01kjr7xqw0kr6fq3sdqjd5e4vy",
    "type": "0",
    "author": "Andrea Michelotti",
    "details": "{\"type\":\"0\"}",
    "timestamp": "2023-11-30T13:48:21.000"
  }
]