{
  "uid": "01kjr72yk6w5jp1sdwkn0657ry",
  "key": "LNFT2-145554",
  "name": "FI7-W-CTR-MOT-001",
  "type": "Motor Controllers",
  "schemaUid": "01kjr6y3bkg7sgffg3kdstpgkq",
  "attributes": {
    "key": "LNFT2-145554",
    "name": "FI7-W-CTR-MOT-001",
    "s/n": "97102912",
    "created": "2026-01-12T17:56:32.000Z",
    "updated": "2026-02-23T13:27:01.000Z",
    "status": "Uninstalled",
    "owner": "LNFMAC-143535",
    "locations": "01kjr7qe4212183j0ceepct95g",
    "facility": "01kjr7st4dyad67rx9rvajqtab",
    "hw_model": "01kjr7k1y2r29a4kd57qjc3ets"
  },
  "relations": {
    "inbound": [],
    "outbound": []
  },
  "attachments": [],
  "metadata": {
    "createdAt": null,
    "updatedAt": null,
    "version": null
  }
}